[
  {
    "annee": "1795",
    "total": 29
  },
  {
    "annee": "1796",
    "total": 647
  },
  {
    "annee": "1797",
    "total": 348
  },
  {
    "annee": "1798",
    "total": 226
  },
  {
    "annee": "1799",
    "total": 237
  },
  {
    "annee": "1800",
    "total": 205
  },
  {
    "annee": "1801",
    "total": 182
  },
  {
    "annee": "1802",
    "total": 172
  },
  {
    "annee": "1803",
    "total": 138
  },
  {
    "annee": "1804",
    "total": 105
  },
  {
    "annee": "1805",
    "total": 88
  },
  {
    "annee": "1806",
    "total": 232
  },
  {
    "annee": "1807",
    "total": 351
  },
  {
    "annee": "1808",
    "total": 335
  },
  {
    "annee": "1809",
    "total": 524
  },
  {
    "annee": "1810",
    "total": 518
  },
  {
    "annee": "1811",
    "total": 624
  },
  {
    "annee": "1812",
    "total": 1068
  },
  {
    "annee": "1813",
    "total": 953
  },
  {
    "annee": "1814",
    "total": 526
  },
  {
    "annee": "1815",
    "total": 555
  },
  {
    "annee": "1816",
    "total": 1168
  },
  {
    "annee": "1817",
    "total": 1630
  },
  {
    "annee": "1818",
    "total": 1768
  },
  {
    "annee": "1819",
    "total": 1298
  },
  {
    "annee": "1820",
    "total": 989
  },
  {
    "annee": "1821",
    "total": 896
  },
  {
    "annee": "1822",
    "total": 470
  },
  {
    "annee": "1823",
    "total": 449
  },
  {
    "annee": "1824",
    "total": 512
  },
  {
    "annee": "1825",
    "total": 539
  },
  {
    "annee": "1826",
    "total": 581
  },
  {
    "annee": "1827",
    "total": 557
  },
  {
    "annee": "1828",
    "total": 587
  },
  {
    "annee": "1829",
    "total": 556
  },
  {
    "annee": "1830",
    "total": 450
  },
  {
    "annee": "1831",
    "total": 315
  },
  {
    "annee": "1832",
    "total": 449
  },
  {
    "annee": "1833",
    "total": 435
  },
  {
    "annee": "1834",
    "total": 583
  },
  {
    "annee": "1835",
    "total": 618
  },
  {
    "annee": "1836",
    "total": 625
  },
  {
    "annee": "1837",
    "total": 567
  },
  {
    "annee": "1838",
    "total": 633
  },
  {
    "annee": "1839",
    "total": 499
  },
  {
    "annee": "1840",
    "total": 529
  },
  {
    "annee": "1841",
    "total": 459
  },
  {
    "annee": "1842",
    "total": 19
  },
  {
    "annee": "1843",
    "total": 2
  },
  {
    "annee": "1844",
    "total": 3
  },
  {
    "annee": "1845",
    "total": 7
  },
  {
    "annee": "1846",
    "total": 6
  },
  {
    "annee": "1847",
    "total": 6
  },
  {
    "annee": "1848",
    "total": 12
  },
  {
    "annee": "1849",
    "total": 4
  },
  {
    "annee": "1850",
    "total": 6
  },
  {
    "annee": "1851",
    "total": 4
  },
  {
    "annee": "1852",
    "total": 7
  },
  {
    "annee": "1860",
    "total": 9
  }
]
